prova_pypi/__init__.py
prova_pypi/prova.py
prova_pypi/model/RotationForest.model
prova_pypi/model/global_features_simply.arff
prova_pypi/utils/models/Result.py
prova_pypi/utils/models/Result.pyc
prova_pypi/utils/models/head.py
prova_pypi/utils/models/head.pyc
prova_pypi/utils/models/joinFile.py
prova_pypi/utils/models/parseWekaOutputFile.py
prova_pypi/utils/models/weka.jar
prova_pypi/utils/models/__pycache__/Result.cpython-310.pyc
prova_pypi/utils/models/__pycache__/head.cpython-310.pyc
prova_pypi/utils/models/__pycache__/joinFile.cpython-310.pyc
prova_pypi/utils/models/__pycache__/parseWekaOutputFile.cpython-310.pyc
prova_pypi/utils/search-mercury/dispatch
prova_pypi/utils/search-mercury/downward
prova_pypi/utils/search-mercury/downward-1
prova_pypi/utils/search-mercury/downward-2
prova_pypi/utils/search-mercury/downward-4
prova_pypi/utils/search-mercury/unitcost
prova_pypi/utils/search-mercury/.obj/additive_heuristic.1.o
prova_pypi/utils/search-mercury/.obj/additive_heuristic.2.o
prova_pypi/utils/search-mercury/.obj/additive_heuristic.4.o
prova_pypi/utils/search-mercury/.obj/axioms.1.o
prova_pypi/utils/search-mercury/.obj/axioms.2.o
prova_pypi/utils/search-mercury/.obj/axioms.4.o
prova_pypi/utils/search-mercury/.obj/causal_graph.1.o
prova_pypi/utils/search-mercury/.obj/causal_graph.2.o
prova_pypi/utils/search-mercury/.obj/causal_graph.4.o
prova_pypi/utils/search-mercury/.obj/combining_evaluator.1.o
prova_pypi/utils/search-mercury/.obj/combining_evaluator.2.o
prova_pypi/utils/search-mercury/.obj/combining_evaluator.4.o
prova_pypi/utils/search-mercury/.obj/domain_transition_graph.1.o
prova_pypi/utils/search-mercury/.obj/domain_transition_graph.2.o
prova_pypi/utils/search-mercury/.obj/domain_transition_graph.4.o
prova_pypi/utils/search-mercury/.obj/exact_timer.1.o
prova_pypi/utils/search-mercury/.obj/exact_timer.2.o
prova_pypi/utils/search-mercury/.obj/exact_timer.4.o
prova_pypi/utils/search-mercury/.obj/ff_heuristic.1.o
prova_pypi-0.0.29.dist-info/METADATA
prova_pypi-0.0.29.dist-info/WHEEL
prova_pypi-0.0.29.dist-info/top_level.txt
prova_pypi-0.0.29.dist-info/RECORD
