Metadata-Version: 2.1
Name: prova-pypi
Version: 0.0.29
Summary: prova_pypi
Author: Isabel Cenamor and Tomas de la Rosa and Fernando Fernandez
Author-email: icenamorg@gmail.com
License: APACHE
Classifier: Operating System :: POSIX :: Linux
Requires-Python: >=3.7
